{
    "metadata": {
        "source": "YoSinTV",
        "updated": "2026-04-17 11:36:43 UTC"
    },
    "matches": [
        {
            "start_time": "11:00",
            "league": "Chinese Super League",
            "country": "China",
            "home": "Qingdao Hainiu",
            "away": "Qingdao West Coast",
            "score": "0 - 0",
            "minute": "1st half",
            "scorers": []
        },
        {
            "start_time": "11:35",
            "league": "Chinese Super League",
            "country": "China",
            "home": "Chongqing Tonglianglong FC",
            "away": "Shenzhen Peng City",
            "score": "0 - 0",
            "minute": "1st half",
            "scorers": []
        },
        {
            "start_time": "11:35",
            "league": "Chinese Super League",
            "country": "China",
            "home": "Shandong Taishan",
            "away": "Shanghai Port",
            "score": "0 - 0",
            "minute": "1st half",
            "scorers": []
        },
        {
            "start_time": "11:30",
            "league": "Super League",
            "country": "India",
            "home": "Chennaiyin FC",
            "away": "Sporting Delhi",
            "score": "0 - 0",
            "minute": "1st half",
            "scorers": []
        },
        {
            "start_time": "11:00",
            "league": "Club Friendly Games",
            "country": "World",
            "home": "BSC Young Boys",
            "away": "Neuch\u00e2tel Xamax",
            "score": "1 - 0",
            "minute": "1st half",
            "scorers": [
                "Darian Male\u0161 13'(H)"
            ]
        },
        {
            "start_time": "10:00",
            "league": "U16 Friendly Games",
            "country": "World",
            "home": "T\u00fcrkiye U16",
            "away": "Northern Ireland U16",
            "score": "1 - 2",
            "minute": "2nd half",
            "scorers": [
                "Unknown 64'(A)",
                "Unknown 42'(A)",
                "Unknown 7'(H)"
            ]
        },
        {
            "start_time": "11:00",
            "league": "U18 Friendly Games, Women",
            "country": "World",
            "home": "T\u00fcrkiye U18",
            "away": "Ethiopia U18",
            "score": "1 - 0",
            "minute": "1st half",
            "scorers": [
                "Unknown 2'(H)"
            ]
        },
        {
            "start_time": "10:00",
            "league": "U23 Friendly Games, Women",
            "country": "World",
            "home": "England U23",
            "away": "Sweden U23",
            "score": "3 - 0",
            "minute": "2nd half",
            "scorers": [
                "Olivia McLoughlin 56'(H)",
                "Hannah Silcock 9'(H)",
                "Isobel Goodwin 4'(H)"
            ]
        },
        {
            "start_time": "11:00",
            "league": "U23 Friendly Games, Women",
            "country": "World",
            "home": "Netherlands U23",
            "away": "Norway U23",
            "score": "0 - 0",
            "minute": "1st half",
            "scorers": []
        },
        {
            "start_time": "11:15",
            "league": "Women Club Friendly Games",
            "country": "World",
            "home": "SK Brann Kvinner",
            "away": "Arna-Bj\u00f8rnar",
            "score": "0 - 0",
            "minute": "1st half",
            "scorers": []
        },
        {
            "start_time": "10:00",
            "league": "U19 UEFA European Championship, W, Q. R2, Gr. B6",
            "country": "Europe",
            "home": "Azerbaijan U19",
            "away": "Georgia U19",
            "score": "1 - 2",
            "minute": "2nd half",
            "scorers": [
                "Natia Jojua 25'(A)",
                "Lolita Kaloiani 9'(A)",
                "Khanim Asadova 6'(H)"
            ]
        },
        {
            "start_time": "10:00",
            "league": "U19 UEFA European Championship, W, Q. R2, Gr. B6",
            "country": "Europe",
            "home": "Czechia U19",
            "away": "Croatia U19",
            "score": "0 - 1",
            "minute": "2nd half",
            "scorers": [
                "Gabrijela Prka\u010din 35'(A)"
            ]
        },
        {
            "start_time": "09:30",
            "league": "U20 Algerian Ligue",
            "country": "Algeria",
            "home": "AS Khroub U20",
            "away": "IRC Setif U20",
            "score": "1 - 0",
            "minute": "2nd half",
            "scorers": [
                "Unknown 77'(H)"
            ]
        },
        {
            "start_time": "10:00",
            "league": "Northern NSW NPL",
            "country": "Australia",
            "home": "Broadmeadow Magic",
            "away": "Cooks Hill United",
            "score": "6 - 0",
            "minute": "2nd half",
            "scorers": [
                "Unknown 41'(H)",
                "Unknown 38'(H)",
                "Unknown 21'(H)",
                "Unknown 20'(H)",
                "Unknown 13'(H)",
                "Unknown 1'(H)"
            ]
        },
        {
            "start_time": "10:00",
            "league": "South Australia NPL",
            "country": "Australia",
            "home": "Croydon FC",
            "away": "West Torrens Birkalla",
            "score": "3 - 0",
            "minute": "2nd half",
            "scorers": [
                "Yuya Kato 61'(H)",
                "Luca Trimboli 54'(H)",
                "Luca Trimboli 39'(H)"
            ]
        },
        {
            "start_time": "11:00",
            "league": "South Australia NPL",
            "country": "Australia",
            "home": "Adelaide Comets",
            "away": "Playford City",
            "score": "0 - 1",
            "minute": "1st half",
            "scorers": [
                "Isaac Mullen 20'(A)"
            ]
        },
        {
            "start_time": "10:00",
            "league": "South Australia NPL, Women",
            "country": "Australia",
            "home": "Campbelltown City SC",
            "away": "Adelaide University",
            "score": "0 - 0",
            "minute": "2nd half",
            "scorers": []
        },
        {
            "start_time": "10:45",
            "league": "South Australia NPL, Women",
            "country": "Australia",
            "home": "Salisbury Inter",
            "away": "West Torrens Birkalla",
            "score": "1 - 0",
            "minute": "1st half",
            "scorers": [
                "Unknown 36'(H)"
            ]
        },
        {
            "start_time": "09:45",
            "league": "Victoria NPL",
            "country": "Australia",
            "home": "Dandenong City FC",
            "away": "Green Gully",
            "score": "2 - 1",
            "minute": "2nd half",
            "scorers": [
                "Unknown 25'(H)",
                "Unknown 21'(A)",
                "Unknown 9'(H)"
            ]
        },
        {
            "start_time": "10:30",
            "league": "Victoria Premier League 2",
            "country": "Australia",
            "home": "Whittlesea United SC",
            "away": "Altona City",
            "score": "0 - 1",
            "minute": "Halftime",
            "scorers": [
                "Unknown 10'(A)"
            ]
        },
        {
            "start_time": "10:30",
            "league": "Victoria NPL, Women",
            "country": "Australia",
            "home": "Spring Hills FC",
            "away": "Boroondara Eagles FC",
            "score": "2 - 1",
            "minute": "Halftime",
            "scorers": [
                "Unknown 42'(H)",
                "Unknown 8'(A)",
                "Unknown 5'(H)"
            ]
        },
        {
            "start_time": "10:30",
            "league": "VPL 1",
            "country": "Australia",
            "home": "Melbourne Knights FC",
            "away": "Manningham United Blues",
            "score": "0 - 0",
            "minute": "2nd half",
            "scorers": []
        },
        {
            "start_time": "10:30",
            "league": "VPL 1",
            "country": "Australia",
            "home": "Northcote City",
            "away": "Port Melbourne Sharks",
            "score": "0 - 0",
            "minute": "2nd half",
            "scorers": []
        },
        {
            "start_time": "10:30",
            "league": "Queensland Premier League 1",
            "country": "Australia",
            "home": "Holland Park Hawks",
            "away": "Capalaba Bulldogs",
            "score": "1 - 0",
            "minute": "2nd half",
            "scorers": [
                "Unknown 29'(H)"
            ]
        },
        {
            "start_time": "10:00",
            "league": "NSW League Two",
            "country": "Australia",
            "home": "Hawkesbury City FC",
            "away": "Camden Tigers",
            "score": "2 - 3",
            "minute": "2nd half",
            "scorers": [
                "Unknown 72'(A)",
                "Unknown 36'(H)",
                "Unknown 29'(A)",
                "Unknown 15'(H)",
                "Unknown 12'(A)"
            ]
        },
        {
            "start_time": "11:00",
            "league": "Northern Territory Premier League",
            "country": "Australia",
            "home": "Mindil Aces",
            "away": "Palmerston Rovers",
            "score": "0 - 0",
            "minute": "1st half",
            "scorers": []
        },
        {
            "start_time": "10:00",
            "league": "NSW League One",
            "country": "Australia",
            "home": "Bankstown City Lions FC",
            "away": "Hills United",
            "score": "2 - 0",
            "minute": "2nd half",
            "scorers": [
                "Unknown 52'(H)",
                "Unknown 13'(H)"
            ]
        },
        {
            "start_time": "10:15",
            "league": "NSW League One",
            "country": "Australia",
            "home": "Blacktown Spartans",
            "away": "Prospect United",
            "score": "1 - 0",
            "minute": "2nd half",
            "scorers": [
                "Unknown 13'(H)"
            ]
        },
        {
            "start_time": "10:00",
            "league": "South Australia State League 1",
            "country": "Australia",
            "home": "Adelaide Olympic",
            "away": "Adelaide Victory",
            "score": "1 - 2",
            "minute": "2nd half",
            "scorers": [
                "Unknown 68'(A)",
                "Unknown 45'(H)",
                "Unknown 31'(A)"
            ]
        },
        {
            "start_time": "10:15",
            "league": "South Australia State League 1",
            "country": "Australia",
            "home": "Eastern United",
            "away": "Adelaide Croatia Raiders",
            "score": "0 - 1",
            "minute": "2nd half",
            "scorers": [
                "Unknown 49'(A)"
            ]
        },
        {
            "start_time": "10:30",
            "league": "Queensland Premier League 2",
            "country": "Australia",
            "home": "Brisbane Knights",
            "away": "Virginia United",
            "score": "0 - 1",
            "minute": "2nd half",
            "scorers": [
                "Unknown 21'(A)"
            ]
        },
        {
            "start_time": "11:00",
            "league": "Western Australia NPL, Women",
            "country": "Australia",
            "home": "Perth Azzurri SC",
            "away": "Balcatta Etna FC",
            "score": "0 - 0",
            "minute": "1st half",
            "scorers": []
        },
        {
            "start_time": "10:30",
            "league": "Queensland Premier League 3 Metro ",
            "country": "Australia",
            "home": "North Pine",
            "away": "Redcliffe Dolphins",
            "score": "3 - 0",
            "minute": "Halftime",
            "scorers": [
                "Unknown 44'(H)",
                "Unknown 18'(H)",
                "Unknown 17'(H)"
            ]
        },
        {
            "start_time": "10:45",
            "league": "South Australia State League, Women",
            "country": "Australia",
            "home": "The Cove FC",
            "away": "Western Strikers",
            "score": "2 - 0",
            "minute": "1st half",
            "scorers": [
                "Unknown 44'(H)",
                "Unknown 2'(H)"
            ]
        },
        {
            "start_time": "11:00",
            "league": "South Australia State League, Women",
            "country": "Australia",
            "home": "Sturt Lions",
            "away": "South Adelaide Panthers FC",
            "score": "0 - 0",
            "minute": "1st half",
            "scorers": []
        },
        {
            "start_time": "10:30",
            "league": "Victoria Premier League, Women ",
            "country": "Australia",
            "home": "Bundoora United",
            "away": "Eltham Redbacks",
            "score": "0 - 0",
            "minute": "Halftime",
            "scorers": []
        },
        {
            "start_time": "10:30",
            "league": "Victoria Premier League, Women ",
            "country": "Australia",
            "home": "Ringwood City",
            "away": "Bayside Argonauts FC",
            "score": "0 - 3",
            "minute": "Halftime",
            "scorers": [
                "Unknown 45'(A)",
                "Unknown 32'(A)",
                "Unknown 29'(A)"
            ]
        },
        {
            "start_time": "10:15",
            "league": "State League 1 North-West",
            "country": "Australia Amateur",
            "home": "Pascoe Vale",
            "away": "Upfield FC",
            "score": "0 - 0",
            "minute": "Started",
            "scorers": []
        },
        {
            "start_time": "10:30",
            "league": "State League 1 North-West",
            "country": "Australia Amateur",
            "home": "Altona East Phoenix SC",
            "away": "FC Clifton Hill",
            "score": "0 - 0",
            "minute": "Started",
            "scorers": []
        },
        {
            "start_time": "10:30",
            "league": "State League 1 North-West",
            "country": "Australia Amateur",
            "home": "Yarraville FC",
            "away": "Westvale Olympic FC",
            "score": "0 - 0",
            "minute": "Started",
            "scorers": []
        },
        {
            "start_time": "10:30",
            "league": "State League 1 South-East",
            "country": "Australia Amateur",
            "home": "Skye United FC",
            "away": "Mornington SC",
            "score": "0 - 0",
            "minute": "Started",
            "scorers": []
        },
        {
            "start_time": "10:30",
            "league": "State League 2 South-East",
            "country": "Australia Amateur",
            "home": "Casey Comets FC",
            "away": "Waverley Wanderers SC",
            "score": "0 - 0",
            "minute": "Started",
            "scorers": []
        },
        {
            "start_time": "10:30",
            "league": "State League 2 South-East",
            "country": "Australia Amateur",
            "home": "Chisholm United",
            "away": "Mooroolbark SC",
            "score": "0 - 0",
            "minute": "Started",
            "scorers": []
        },
        {
            "start_time": "10:30",
            "league": "State League 2 South-East",
            "country": "Australia Amateur",
            "home": "Noble Park United FC",
            "away": "Berwick City SC",
            "score": "0 - 0",
            "minute": "Started",
            "scorers": []
        },
        {
            "start_time": "10:30",
            "league": "State League 2 North-West",
            "country": "Australia Amateur",
            "home": "Brimbank Stallions FC",
            "away": "Mill Park SC",
            "score": "0 - 0",
            "minute": "Started",
            "scorers": []
        },
        {
            "start_time": "10:30",
            "league": "State League 4 North-West",
            "country": "Australia Amateur",
            "home": "Point Cook",
            "away": "Westside Strikers FC",
            "score": "0 - 0",
            "minute": "Started",
            "scorers": []
        },
        {
            "start_time": "10:30",
            "league": "State League 4 South-East",
            "country": "Australia Amateur",
            "home": "Springvale City SC",
            "away": "Ashburton United SC",
            "score": "0 - 0",
            "minute": "Started",
            "scorers": []
        },
        {
            "start_time": "10:00",
            "league": "South Coast Premier League 1",
            "country": "Australia Amateur",
            "home": "Cringila Lions FC",
            "away": "Wollongong Olympic FC",
            "score": "0 - 0",
            "minute": "Started",
            "scorers": []
        },
        {
            "start_time": "09:30",
            "league": "Premier League",
            "country": "Bangladesh",
            "home": "Mohammedan SC",
            "away": "Fakirerpool Young Men",
            "score": "3 - 0",
            "minute": "2nd half",
            "scorers": [
                "Rafayel Tudu 90'(H)",
                "Mohammed Jewel Mia 90'(H)",
                "Md Joy Ahamed 60'(H)"
            ]
        },
        {
            "start_time": "11:00",
            "league": "U19 1. Liga",
            "country": "Czech Republic",
            "home": "FC Zbrojovka Brno U19",
            "away": "Vyso\u010dina Jihlava U19",
            "score": "1 - 0",
            "minute": "1st half",
            "scorers": [
                "Unknown 19'(H)"
            ]
        },
        {
            "start_time": "11:00",
            "league": "D1 Djibouti",
            "country": "Djibouti",
            "home": "Gendarmerie Nationale",
            "away": "Arta/Solar7",
            "score": "0 - 0",
            "minute": "Started",
            "scorers": []
        },
        {
            "start_time": "11:00",
            "league": "Hungary U19 1st Division",
            "country": "Hungary",
            "home": "Budapest Honv\u00e9d U19",
            "away": "Ill\u00e9s Akad\u00e9mia Halad\u00e1s U19",
            "score": "1 - 0",
            "minute": "1st half",
            "scorers": [
                "Unknown 22'(H)"
            ]
        },
        {
            "start_time": "10:30",
            "league": "I-League",
            "country": "India",
            "home": "Namdhari FC",
            "away": "Chanmari FC",
            "score": "0 - 1",
            "minute": "2nd half",
            "scorers": [
                "Luca Pedro 4'(A)"
            ]
        },
        {
            "start_time": "11:00",
            "league": "Kerala Premier Leagues, Group B",
            "country": "India Amateur",
            "home": "Kerala United FC",
            "away": "Parappur FC",
            "score": "0 - 0",
            "minute": "Started",
            "scorers": []
        },
        {
            "start_time": "10:30",
            "league": "Goa Pro League, Championship Round",
            "country": "India Amateur",
            "home": "SC de Goa",
            "away": "Sesa FA",
            "score": "0 - 0",
            "minute": "Halftime",
            "scorers": []
        },
        {
            "start_time": "10:00",
            "league": "J2/J3 League, West A",
            "country": "Japan",
            "home": "FC Osaka",
            "away": "Ehime FC",
            "score": "0 - 1",
            "minute": "2nd half",
            "scorers": [
                "Kazuya Mima 6'(A)"
            ]
        },
        {
            "start_time": "10:00",
            "league": "Pervaya Liga",
            "country": "Kazakhstan",
            "home": "Aktobe Reserve",
            "away": "Taraz",
            "score": "1 - 0",
            "minute": "2nd half",
            "scorers": [
                "Doszhan Arystanov 60'(H)"
            ]
        },
        {
            "start_time": "10:00",
            "league": "Pervaya Liga",
            "country": "Kazakhstan",
            "home": "FC Yelimay Reserve",
            "away": "FC Khan Tengri",
            "score": "3 - 2",
            "minute": "2nd half",
            "scorers": [
                "Unknown 48'(H)",
                "Alizhan Baygaliyev 24'(H)",
                "Nurdaulet Amirbek 18'(A)",
                "Unknown 5'(H)",
                "Rustam Emirov 2'(A)"
            ]
        },
        {
            "start_time": "10:00",
            "league": "Pervaya Liga",
            "country": "Kazakhstan",
            "home": "Shakhter Karagandy",
            "away": "Batyr Ekibastuz",
            "score": "3 - 0",
            "minute": "2nd half",
            "scorers": [
                "Kasymzhan Taipov 62'(H)",
                "Vladislav Prokopenko 51'(H)",
                "Alen Aymanov 35'(H)"
            ]
        },
        {
            "start_time": "11:00",
            "league": "Pervaya Liga",
            "country": "Kazakhstan",
            "home": "Akademiya Ontustik",
            "away": "FC Tobol Kostanay Reserve",
            "score": "1 - 0",
            "minute": "1st half",
            "scorers": [
                "Unknown 35'(H)"
            ]
        },
        {
            "start_time": "11:00",
            "league": "1. MFL",
            "country": "North Macedonia",
            "home": "FK Sileks Kratovo",
            "away": "AP Brera Strumica",
            "score": "1 - 0",
            "minute": "1st half",
            "scorers": [
                "Unknown 19'(H)"
            ]
        },
        {
            "start_time": "10:00",
            "league": " M-League",
            "country": "Russia",
            "home": "Akron Akademia Konoplev",
            "away": "Dynamo Moscow Youth",
            "score": "3 - 0",
            "minute": "2nd half",
            "scorers": [
                "Unknown 57'(H)",
                "Unknown 46'(H)",
                "Unknown 41'(H)"
            ]
        },
        {
            "start_time": "10:00",
            "league": " M-League",
            "country": "Russia",
            "home": "Chertanovo Moscow Youth",
            "away": "Lokomotiv Moscow Youth",
            "score": "2 - 2",
            "minute": "2nd half",
            "scorers": [
                "Zakhar Evdachev 49'(H)",
                "Zakhar Evdachev 45'(H)",
                "Kirill Komarov 17'(A)",
                "Artem Semin 13'(A)"
            ]
        },
        {
            "start_time": "10:00",
            "league": "M-League, Division B",
            "country": "Russia Amateur",
            "home": "Master-Saturn Egorjevsk",
            "away": "Spartak Kostroma Youth",
            "score": "0 - 0",
            "minute": "Started",
            "scorers": []
        },
        {
            "start_time": "10:00",
            "league": "M-League, Division B",
            "country": "Russia Amateur",
            "home": "Shinnik Yaroslavl Youth",
            "away": "Vityaz Podolsk Youth",
            "score": "1 - 0",
            "minute": "2nd half",
            "scorers": [
                "Unknown 35'(H)"
            ]
        },
        {
            "start_time": "11:00",
            "league": "M-League, Division B",
            "country": "Russia Amateur",
            "home": "Baltika Kaliningrad Youth",
            "away": "Kirovets-Voskhozhdenie St. Petersburg Youth",
            "score": "0 - 0",
            "minute": "1st half",
            "scorers": []
        },
        {
            "start_time": "11:00",
            "league": "M-League, Division B",
            "country": "Russia Amateur",
            "home": "SSHOR Zenit St. Petersburg",
            "away": "Chernomorets Novorossijsk Youth",
            "score": "0 - 0",
            "minute": "Started",
            "scorers": []
        },
        {
            "start_time": "11:30",
            "league": "Premier League",
            "country": "Singapore",
            "home": "Tampines Rovers",
            "away": "Balestier Khalsa",
            "score": "0 - 0",
            "minute": "1st half",
            "scorers": []
        },
        {
            "start_time": "10:00",
            "league": "WK League",
            "country": "South Korea",
            "home": "Incheon Hyundai Steel Red Angels",
            "away": "Suwon WFC",
            "score": "1 - 1",
            "minute": "2nd half",
            "scorers": [
                "Haruhi Suzuki 44'(A)",
                "Kim Myeong-jin 20'(H)"
            ]
        },
        {
            "start_time": "10:00",
            "league": "WK League",
            "country": "South Korea",
            "home": "Seoul City WFC",
            "away": "Sejong Sportstoto WFC",
            "score": "2 - 1",
            "minute": "2nd half",
            "scorers": [
                "Unknown 71'(A)",
                "Unknown 70'(H)",
                "Unknown 66'(H)"
            ]
        },
        {
            "start_time": "11:00",
            "league": "Premier League",
            "country": "South Sudan",
            "home": "Kator FC",
            "away": "Olympic Renk",
            "score": "2 - 0",
            "minute": "1st half",
            "scorers": [
                "Unknown 23'(H)"
            ]
        },
        {
            "start_time": "10:00",
            "league": "U16 Geli\u015fim Ligi, Playoff Ma\u00e7lar\u0131",
            "country": "Turkey Amateur",
            "home": "Alanyaspor U16",
            "away": "Gaziantep FK U16",
            "score": "0 - 0",
            "minute": "Started",
            "scorers": []
        },
        {
            "start_time": "10:00",
            "league": "U16 Geli\u015fim Ligi, Playoff Ma\u00e7lar\u0131",
            "country": "Turkey Amateur",
            "home": "Amed Sportif Faaliyetler U16",
            "away": "Vanspor FK U16",
            "score": "0 - 0",
            "minute": "Started",
            "scorers": []
        },
        {
            "start_time": "10:00",
            "league": "U16 Geli\u015fim Ligi, Playoff Ma\u00e7lar\u0131",
            "country": "Turkey Amateur",
            "home": "Antalyaspor U16",
            "away": "Adana Demirspor U16",
            "score": "0 - 0",
            "minute": "Started",
            "scorers": []
        },
        {
            "start_time": "10:00",
            "league": "U16 Geli\u015fim Ligi, Playoff Ma\u00e7lar\u0131",
            "country": "Turkey Amateur",
            "home": "Bursa Y\u0131ld\u0131r\u0131mspor U16",
            "away": "Denizli \u0130dman Yurdu 1959 SK U16",
            "score": "0 - 0",
            "minute": "Started",
            "scorers": []
        },
        {
            "start_time": "10:00",
            "league": "U16 Geli\u015fim Ligi, Playoff Ma\u00e7lar\u0131",
            "country": "Turkey Amateur",
            "home": "Diyarbak\u0131r DS\u0130 U16",
            "away": "Tatvan Gen\u00e7lerbirli\u011fi U16",
            "score": "0 - 0",
            "minute": "Started",
            "scorers": []
        },
        {
            "start_time": "10:00",
            "league": "U16 Geli\u015fim Ligi, Playoff Ma\u00e7lar\u0131",
            "country": "Turkey Amateur",
            "home": "Karacabey Belediye Spor U16",
            "away": "G\u00f6ztepe U16",
            "score": "0 - 0",
            "minute": "Started",
            "scorers": []
        },
        {
            "start_time": "10:00",
            "league": "U16 Geli\u015fim Ligi, Playoff Ma\u00e7lar\u0131",
            "country": "Turkey Amateur",
            "home": "Ke\u00e7i\u00f6reng\u00fcc\u00fc U16",
            "away": "Afyonkarahisar Ege Gen\u00e7lik U16",
            "score": "0 - 0",
            "minute": "Started",
            "scorers": []
        },
        {
            "start_time": "10:00",
            "league": "U16 Geli\u015fim Ligi, Playoff Ma\u00e7lar\u0131",
            "country": "Turkey Amateur",
            "home": "Samsunspor U16",
            "away": "D\u00fczcespor U16",
            "score": "0 - 0",
            "minute": "Started",
            "scorers": []
        },
        {
            "start_time": "10:00",
            "league": "U16 Geli\u015fim Ligi, Playoff Ma\u00e7lar\u0131",
            "country": "Turkey Amateur",
            "home": "\u00c7aykur Rizespor U16",
            "away": "Boluspor U16",
            "score": "0 - 0",
            "minute": "Started",
            "scorers": []
        },
        {
            "start_time": "10:00",
            "league": "U16 Geli\u015fim Ligi, Playoff Ma\u00e7lar\u0131",
            "country": "Turkey Amateur",
            "home": "Bulvarspor U16",
            "away": "Beylerbeyi 1911 FK U16",
            "score": "0 - 0",
            "minute": "Started",
            "scorers": []
        },
        {
            "start_time": "10:00",
            "league": "U16 Geli\u015fim Ligi, Playoff Ma\u00e7lar\u0131",
            "country": "Turkey Amateur",
            "home": "Derince Birlikspor U16",
            "away": "\u015e\u00fckr\u00fcpa\u015fa U16",
            "score": "0 - 0",
            "minute": "Started",
            "scorers": []
        },
        {
            "start_time": "10:00",
            "league": "U16 Geli\u015fim Ligi, Playoff Ma\u00e7lar\u0131",
            "country": "Turkey Amateur",
            "home": "Pendikspor U16",
            "away": "Ayaza\u011faspor U16",
            "score": "0 - 0",
            "minute": "Started",
            "scorers": []
        },
        {
            "start_time": "10:00",
            "league": "U16 Geli\u015fim Ligi, Playoff Ma\u00e7lar\u0131",
            "country": "Turkey Amateur",
            "home": "\u00c7orlu Belediye FK U16",
            "away": "Bursaspor U16",
            "score": "0 - 0",
            "minute": "Started",
            "scorers": []
        },
        {
            "start_time": "10:00",
            "league": "U19 Geli\u015fim Ligi - Playoff Ma\u00e7lar\u0131",
            "country": "Turkey Amateur",
            "home": "Ankara Ke\u00e7i\u00f6reng\u00fcc\u00fc U19",
            "away": "Sebat Gen\u00e7lik Spor U19",
            "score": "0 - 0",
            "minute": "Started",
            "scorers": []
        },
        {
            "start_time": "10:00",
            "league": "U19 Geli\u015fim Ligi - Playoff Ma\u00e7lar\u0131",
            "country": "Turkey Amateur",
            "home": "Ayd\u0131n B\u00fcy\u00fck\u015fehir Belediyespor U19",
            "away": "Sel\u00e7uklu Belediyespor U19",
            "score": "0 - 0",
            "minute": "Started",
            "scorers": []
        },
        {
            "start_time": "10:00",
            "league": "U19 Geli\u015fim Ligi - Playoff Ma\u00e7lar\u0131",
            "country": "Turkey Amateur",
            "home": "D\u00fczcespor U19",
            "away": "Yomraspor U19",
            "score": "0 - 0",
            "minute": "Started",
            "scorers": []
        },
        {
            "start_time": "10:00",
            "league": "U19 Geli\u015fim Ligi - Playoff Ma\u00e7lar\u0131",
            "country": "Turkey Amateur",
            "home": "MKE Ankarag\u00fcc\u00fc U19",
            "away": "Orduspor 1967 U19",
            "score": "0 - 0",
            "minute": "Started",
            "scorers": []
        },
        {
            "start_time": "10:00",
            "league": "U19 Geli\u015fim Ligi - Playoff Ma\u00e7lar\u0131",
            "country": "Turkey Amateur",
            "home": "Somaspor U19",
            "away": "Bodrum FK U19",
            "score": "0 - 3",
            "minute": "2nd half",
            "scorers": [
                "Unknown 38'(A)",
                "Unknown 19'(A)",
                "Unknown 8'(A)"
            ]
        },
        {
            "start_time": "10:00",
            "league": "U19 Geli\u015fim Ligi - Playoff Ma\u00e7lar\u0131",
            "country": "Turkey Amateur",
            "home": "Arnavutk\u00f6y Belediye FSK U19",
            "away": "Eski\u015fehirspor U19",
            "score": "0 - 0",
            "minute": "Started",
            "scorers": []
        },
        {
            "start_time": "10:00",
            "league": "U19 Geli\u015fim Ligi - Playoff Ma\u00e7lar\u0131",
            "country": "Turkey Amateur",
            "home": "Esenler Erokspor U19",
            "away": "Band\u0131rmaspor U19",
            "score": "0 - 0",
            "minute": "Started",
            "scorers": []
        },
        {
            "start_time": "10:00",
            "league": "U19 Geli\u015fim Ligi - Playoff Ma\u00e7lar\u0131",
            "country": "Turkey Amateur",
            "home": "Sultanbeyli Belediyespor U19",
            "away": "Guzide Gebzespor U19",
            "score": "1 - 0",
            "minute": "Started",
            "scorers": [
                "Unknown 45'(H)"
            ]
        },
        {
            "start_time": "11:00",
            "league": "Persha Liga",
            "country": "Ukraine",
            "home": "FC Metalist Kharkiv",
            "away": "Bukovyna Chernivtsi",
            "score": "0 - 2",
            "minute": "1st half",
            "scorers": [
                "Vitalii Dakhnovskyi 12'(A)"
            ]
        },
        {
            "start_time": "10:00",
            "league": "U19 Championship",
            "country": "Ukraine",
            "home": "Kolos Kovalivka U19",
            "away": "LNZ Cherkasy U19",
            "score": "1 - 0",
            "minute": "2nd half",
            "scorers": [
                "Unknown 41'(H)"
            ]
        },
        {
            "start_time": "10:00",
            "league": "U19 Championship",
            "country": "Ukraine",
            "home": "Metalist 1925 U19",
            "away": "FK Kudrivka U19",
            "score": "2 - 1",
            "minute": "2nd half",
            "scorers": [
                "Unknown 33'(H)",
                "Yaroslav Vakhil 11'(A)",
                "Unknown 9'(H)"
            ]
        },
        {
            "start_time": "10:00",
            "league": "V-League 2",
            "country": "Vietnam",
            "home": "Kh\u00e1nh Ho\u00e0",
            "away": "Thanh Ni\u00ean H\u1ed3 Ch\u00ed Minh City",
            "score": "2 - 1",
            "minute": "2nd half",
            "scorers": [
                "Unknown 31'(H)",
                "Unknown 22'(H)",
                "Unknown 1'(A)"
            ]
        }
    ]
}