{
    "metadata": {
        "source": "YoSinTV",
        "updated": "2026-01-20 17:16:41 UTC"
    },
    "matches": [
        {
            "start_time": "15:30",
            "league": "UEFA Champions League",
            "country": "Europe",
            "home": "Kairat Almaty",
            "away": "Club Brugge KV",
            "score": "0 - 4",
            "minute": "2nd half",
            "scorers": [
                "Brandon Mechele 84'(A)",
                "Romeo Vermant 74'(A)",
                "Hans Vanaken 38'(A)",
                "Aleksandar Stankovi\u0107 32'(A)"
            ]
        },
        {
            "start_time": "15:30",
            "league": "Club Friendly Games",
            "country": "World",
            "home": "GKS Katowice",
            "away": "FK TSC Ba\u010dka Topola",
            "score": "2 - 1",
            "minute": "2nd half",
            "scorers": [
                "Adrian B\u0142\u0105d 88'(H)",
                "Unknown 69'(A)",
                "Mateusz Wdowiak 21'(H)"
            ]
        },
        {
            "start_time": "16:00",
            "league": "Club Friendly Games",
            "country": "World",
            "home": "First Vienna FC",
            "away": "SR Donaufeld",
            "score": "3 - 3",
            "minute": "2nd half",
            "scorers": [
                "Unknown 66'(A)",
                "Unknown 64'(A)",
                "Unknown 44'(H)",
                "Unknown 28'(H)",
                "Unknown 25'(A)",
                "Unknown 19'(H)"
            ]
        },
        {
            "start_time": "16:30",
            "league": "Club Friendly Games",
            "country": "World",
            "home": "Kapfenberger SV",
            "away": "SC Weiz",
            "score": "1 - 0",
            "minute": "Halftime",
            "scorers": [
                "Unknown 4'(H)"
            ]
        },
        {
            "start_time": "16:30",
            "league": "Club Friendly Games",
            "country": "World",
            "home": "Middelfart",
            "away": "Naesby",
            "score": "0 - 0",
            "minute": "1st half",
            "scorers": []
        },
        {
            "start_time": "16:30",
            "league": "Club Friendly Games",
            "country": "World",
            "home": "Universitario de Deportes",
            "away": "Melgar",
            "score": "0 - 1",
            "minute": "2nd half",
            "scorers": [
                "Unknown 15'(A)"
            ]
        },
        {
            "start_time": "17:00",
            "league": "Club Friendly Games",
            "country": "World",
            "home": "BSG Chemie Leipzig",
            "away": "Union Sandersdorf",
            "score": "0 - 0",
            "minute": "1st half",
            "scorers": []
        },
        {
            "start_time": "17:00",
            "league": "Club Friendly Games",
            "country": "World",
            "home": "MFK Tatran Liptovsk\u00fd Mikul\u00e1\u0161",
            "away": "M\u0160K N\u00e1mestovo",
            "score": "2 - 1",
            "minute": "1st half",
            "scorers": [
                "Unknown 14'(H)",
                "Unknown 9'(A)",
                "Unknown 4'(H)"
            ]
        },
        {
            "start_time": "15:30",
            "league": "U23 AFC Asian Cup, Knockout stage",
            "country": "Asia",
            "home": "Vietnam U23",
            "away": "China U23",
            "score": "0 - 2",
            "minute": "2nd half",
            "scorers": [
                "Yuwang Xiang 52'(A)",
                "Peng Xiao 48'(A)"
            ]
        },
        {
            "start_time": "17:00",
            "league": "Coppa Italia, Women",
            "country": "Italy",
            "home": "Milan",
            "away": "Fiorentina",
            "score": "0 - 1",
            "minute": "1st half",
            "scorers": [
                "Emilie Woldvik 10'(A)"
            ]
        },
        {
            "start_time": "17:00",
            "league": "Primavera 1",
            "country": "Italy",
            "home": "Inter U20",
            "away": "Monza U20",
            "score": "0 - 1",
            "minute": "1st half",
            "scorers": [
                "Lorenzo Colonnese 2'(A)"
            ]
        },
        {
            "start_time": "15:30",
            "league": "Bahrain U21 League",
            "country": "Bahrain",
            "home": "Al-Ittihad Bahrain U21",
            "away": "Al Riffa U21",
            "score": "1 - 2",
            "minute": "2nd half",
            "scorers": [
                "Unknown 51'(H)",
                "Unknown 17'(A)",
                "Unknown 7'(A)"
            ]
        },
        {
            "start_time": "15:30",
            "league": "Bahrain U21 League",
            "country": "Bahrain",
            "home": "Al Khalidiyah U21",
            "away": "East Riffa U21",
            "score": "1 - 0",
            "minute": "2nd half",
            "scorers": [
                "Unknown 24'(H)"
            ]
        },
        {
            "start_time": "15:30",
            "league": "Bahrain U21 League",
            "country": "Bahrain",
            "home": "Bouri Cultural U21",
            "away": "Al-Najma U21",
            "score": "1 - 3",
            "minute": "2nd half",
            "scorers": [
                "Unknown 67'(A)",
                "Unknown 50'(A)",
                "Unknown 32'(A)",
                "Unknown 31'(H)"
            ]
        },
        {
            "start_time": "16:00",
            "league": "Bulgaria Friendly Games",
            "country": "Bulgaria Amateur",
            "home": "FC Lyulin Sofia",
            "away": "FC Levski-Rakovski Sofia",
            "score": "1 - 0",
            "minute": "Started",
            "scorers": [
                "Unknown 45'(H)"
            ]
        },
        {
            "start_time": "15:30",
            "league": "Coupe du Faso",
            "country": "Burkina Faso",
            "home": "Salitas FC",
            "away": "Real du Faso",
            "score": "0 - 3",
            "minute": "2nd half",
            "scorers": [
                "Unknown 79'(A)",
                "Unknown 19'(A)",
                "Unknown 5'(A)"
            ]
        },
        {
            "start_time": "16:00",
            "league": "GFF First Division",
            "country": "Gambia",
            "home": "Brikama United FC",
            "away": "Team Rhino FC",
            "score": "0 - 0",
            "minute": "2nd half",
            "scorers": []
        },
        {
            "start_time": "16:00",
            "league": "GFF First Division",
            "country": "Gambia",
            "home": "Gambian Dutch Lions",
            "away": "Greater Tomorrow FC",
            "score": "0 - 0",
            "minute": "2nd half",
            "scorers": []
        },
        {
            "start_time": "16:00",
            "league": "GFF First Division",
            "country": "Gambia",
            "home": "Hart Academy FC",
            "away": "Bombada FC",
            "score": "0 - 1",
            "minute": "2nd half",
            "scorers": [
                "Unknown 39'(A)"
            ]
        },
        {
            "start_time": "16:00",
            "league": "GFF First Division",
            "country": "Gambia",
            "home": "Hawks FC",
            "away": "Steve Biko FC",
            "score": "0 - 0",
            "minute": "Halftime",
            "scorers": []
        },
        {
            "start_time": "16:00",
            "league": "GFF First Division",
            "country": "Gambia",
            "home": "Real De Banjul",
            "away": "TMT FA",
            "score": "0 - 1",
            "minute": "2nd half",
            "scorers": [
                "Unknown 33'(A)"
            ]
        },
        {
            "start_time": "16:30",
            "league": "U19 Premier League, Relegation Round",
            "country": "Israel",
            "home": "Hapoel Nir Ramat Hasharon U19",
            "away": "Ashdod FC U19",
            "score": "0 - 0",
            "minute": "1st half",
            "scorers": []
        },
        {
            "start_time": "16:30",
            "league": "Premier League, Group 1",
            "country": "Libya",
            "home": "Al Dahra Tripoli FC",
            "away": "Al Ahli Tripoli",
            "score": "0 - 1",
            "minute": "1st half",
            "scorers": [
                "Ezzeddine Al Mariami 6'(A)"
            ]
        },
        {
            "start_time": "16:30",
            "league": "Premier League, Group 1",
            "country": "Libya",
            "home": "Assabah SC",
            "away": "Al Khums SC",
            "score": "0 - 0",
            "minute": "1st half",
            "scorers": []
        },
        {
            "start_time": "16:00",
            "league": "Ligue 1",
            "country": "Mali",
            "home": "AS Bakaridjan",
            "away": "Union Sportive Bougouba",
            "score": "1 - 1",
            "minute": "2nd half",
            "scorers": [
                "Unknown 27'(H)",
                "Unknown 15'(A)"
            ]
        },
        {
            "start_time": "16:00",
            "league": "Super D1",
            "country": "Mauritania",
            "home": "FC Nouadhibou",
            "away": "Ka\u00e9di FC",
            "score": "0 - 0",
            "minute": "2nd half",
            "scorers": []
        },
        {
            "start_time": "16:00",
            "league": "Super D2",
            "country": "Mauritania",
            "home": "Star Arafat",
            "away": "AS Armee",
            "score": "1 - 0",
            "minute": "2nd half",
            "scorers": [
                "Unknown 37'(H)"
            ]
        },
        {
            "start_time": "16:15",
            "league": "Sultan Cup",
            "country": "Oman",
            "home": "Al Seeb SC",
            "away": "Al Nahda SC",
            "score": "1 - 0",
            "minute": "Halftime",
            "scorers": [
                "Unknown 45'(H)"
            ]
        },
        {
            "start_time": "15:30",
            "league": "QSL Cup",
            "country": "Qatar",
            "home": "Al Kharaitiyat SC",
            "away": "Al Shamal SC",
            "score": "1 - 3",
            "minute": "2nd half",
            "scorers": [
                "Unknown 81'(H)",
                "Unknown 44'(A)",
                "Unknown 21'(A)",
                "Unknown 17'(A)"
            ]
        },
        {
            "start_time": "15:30",
            "league": "QSL Cup",
            "country": "Qatar",
            "home": "Al Waab FC",
            "away": "Al-Shahaniya",
            "score": "1 - 1",
            "minute": "2nd half",
            "scorers": [
                "Unknown 48'(A)",
                "Abdul Rahman Ragab 22'(H)"
            ]
        },
        {
            "start_time": "12:15",
            "league": "Second Division League - Group 1",
            "country": "Saudi Arabia",
            "home": "Al-Taraji",
            "away": "Al-Sadd",
            "score": "2 - 2",
            "minute": "2nd half",
            "scorers": [
                "Unknown 84'(H)",
                "Unknown 54'(A)",
                "Unknown 36'(A)"
            ]
        },
        {
            "start_time": "12:50",
            "league": "Second Division League - Group 1",
            "country": "Saudi Arabia",
            "home": "Najran",
            "away": "Al-Ain",
            "score": "2 - 0",
            "minute": "2nd half",
            "scorers": []
        },
        {
            "start_time": "16:00",
            "league": "Premier League",
            "country": "Tanzania",
            "home": "Singida Black Stars SC",
            "away": "JKT Tanzania",
            "score": "0 - 0",
            "minute": "2nd half",
            "scorers": []
        },
        {
            "start_time": "15:00",
            "league": "Diyarbak\u0131r 1. Amat\u00f6r Ligi, Group 1",
            "country": "Turkey Amateur",
            "home": "Yeni\u015fehir Harb \u0130\u015f",
            "away": "\u00d6zbek Budakspor",
            "score": "1 - 7",
            "minute": "Started",
            "scorers": [
                "Unknown 86'(A)",
                "Unknown 81'(A)",
                "Unknown 55'(A)",
                "Unknown 50'(A)",
                "Unknown 42'(A)",
                "Unknown 37'(H)",
                "Unknown 21'(A)",
                "Unknown 4'(A)"
            ]
        },
        {
            "start_time": "17:00",
            "league": "Diyarbak\u0131r 1. Amat\u00f6r Ligi, Group 1",
            "country": "Turkey Amateur",
            "home": "Diyarbak\u0131r Demirspor",
            "away": "\u00d6z Diyar Gen\u00e7lik",
            "score": "0 - 0",
            "minute": "Started",
            "scorers": []
        },
        {
            "start_time": "15:00",
            "league": "Diyarbak\u0131r 1. Amat\u00f6r Ligi, Group 2",
            "country": "Turkey Amateur",
            "home": "Diyar 21 Spor",
            "away": "Sur Ba\u011f\u0131var Gen\u00e7lik",
            "score": "2 - 5",
            "minute": "Started",
            "scorers": [
                "Unknown 89'(A)",
                "Unknown 85'(A)",
                "Unknown 65'(H)",
                "Unknown 56'(H)",
                "Unknown 39'(A)",
                "Unknown 36'(A)",
                "Unknown 5'(A)"
            ]
        },
        {
            "start_time": "17:00",
            "league": "Diyarbak\u0131r 1. Amat\u00f6r Ligi, Group 2",
            "country": "Turkey Amateur",
            "home": "Diyarbak\u0131r Seyrantepespor",
            "away": "\u00d6z Hevsel Gen\u00e7likspor",
            "score": "0 - 0",
            "minute": "Started",
            "scorers": []
        },
        {
            "start_time": "16:00",
            "league": "MLS Pre Season",
            "country": "USA",
            "home": "Nashville SC",
            "away": "Chicago Fire",
            "score": "0 - 3",
            "minute": "2nd half",
            "scorers": [
                "Philip Zinckernagel 46'(A)",
                "Unknown 20'(A)",
                "David Poreba 5'(A)"
            ]
        }
    ]
}